{
  "editor:set-heading-1": [
    {
      "modifiers": [
        "Mod",
        "Shift"
      ],
      "key": "1"
    }
  ],
  "editor:set-heading-2": [
    {
      "modifiers": [
        "Mod",
        "Shift"
      ],
      "key": "2"
    }
  ],
  "insert-template": [
    {
      "modifiers": [
        "Alt",
        "Shift"
      ],
      "key": "T"
    }
  ],
  "app:toggle-left-sidebar": [
    {
      "modifiers": [
        "Alt",
        "Shift"
      ],
      "key": "1"
    }
  ],
  "app:toggle-right-sidebar": [
    {
      "modifiers": [
        "Alt",
        "Shift"
      ],
      "key": "2"
    }
  ],
  "markdown:add-metadata-property": [
    {
      "modifiers": [
        "Mod",
        "Shift"
      ],
      "key": ","
    }
  ],
  "editor:toggle-fold-properties": [
    {
      "modifiers": [
        "Mod",
        "Shift"
      ],
      "key": "P"
    }
  ],
  "window:zoom-in": [
    {
      "modifiers": [
        "Mod"
      ],
      "key": "="
    }
  ],
  "editor:toggle-bullet-list": [
    {
      "modifiers": [
        "Mod",
        "Shift"
      ],
      "key": "B"
    }
  ],
  "readwise-official:readwise-official-sync": [
    {
      "modifiers": [
        "Mod",
        "Shift"
      ],
      "key": "R"
    }
  ],
  "editor:toggle-checklist-status": [],
  "graph:open-local": [
    {
      "modifiers": [
        "Mod"
      ],
      "key": "L"
    }
  ],
  "audio-recorder:start": [
    {
      "modifiers": [
        "Mod"
      ],
      "key": ";"
    }
  ],
  "audio-recorder:stop": [
    {
      "modifiers": [
        "Mod"
      ],
      "key": "'"
    }
  ],
  "workspace:undo-close-pane": [],
  "obsidian-timestamper:obsidian-fast-timestamp": [
    {
      "modifiers": [
        "Mod",
        "Shift"
      ],
      "key": "T"
    }
  ],
  "homepage:open-homepage": [
    {
      "modifiers": [
        "Mod"
      ],
      "key": "H"
    }
  ],
  "obsidian-timestamper:obsidian-fast-datestamp": [
    {
      "modifiers": [
        "Mod",
        "Shift"
      ],
      "key": "D"
    }
  ],
  "app:reload": [
    {
      "modifiers": [
        "Mod"
      ],
      "key": "R"
    }
  ],
  "editor:unfold-all": [
    {
      "modifiers": [
        "Mod",
        "Shift"
      ],
      "key": "O"
    }
  ],
  "editor:fold-all": [
    {
      "modifiers": [
        "Mod",
        "Shift"
      ],
      "key": "I"
    }
  ]
}