{
  "headers": {
    "content-security-policy": "default-src 'none'; style-src 'unsafe-inline'; sandbox",
    "cache-control": "public, max-age=31536000, immutable",
    "content-type": "application/typescript; charset=utf-8",
    "referrer-policy": "strict-origin-when-cross-origin",
    "access-control-allow-origin": "*",
    "x-amz-cf-id": "KpltHhzvy_Xt4mPYE5cNrFVGCXAaL6dzIeltSg0sKAi9qkEH6aVGTQ==",
    "x-amz-version-id": "cY42HvzivrroS3hvw0mSOa15_zspqRFb",
    "age": "17201253",
    "via": "http/2 edgeproxy-h",
    "x-amz-replication-status": "COMPLETED",
    "x-cache": "Hit from cloudfront",
    "cross-origin-opener-policy": "same-origin",
    "cross-origin-resource-policy": "same-origin",
    "server-timing": "fetchSource;dur=222",
    "x-frame-options": "DENY",
    "vary": "Accept-Encoding, Origin",
    "accept-ranges": "bytes",
    "x-content-type-options": "nosniff",
    "x-amz-cf-pop": "AMS50-C1",
    "content-length": "354",
    "server": "deno/gcp-europe-west4",
    "strict-transport-security": "max-age=63072000; includeSubDomains; preload",
    "cross-origin-embedder-policy": "same-origin",
    "last-modified": "Fri, 25 Mar 2022 13:32:48 GMT",
    "etag": "\"bb29a34b93be1b313ab97913ad6bd902\"",
    "date": "Sun, 02 Jul 2023 11:38:24 GMT"
  },
  "url": "https://deno.land/std@0.132.0/node/_fs/_fs_unlink.ts",
  "now": {
    "secs_since_epoch": 1705499160,
    "nanos_since_epoch": 155536092
  }
}