{
  "headers": {
    "cache-control": "public, max-age=31536000, immutable",
    "accept-ranges": "bytes",
    "cross-origin-resource-policy": "same-origin",
    "referrer-policy": "strict-origin-when-cross-origin",
    "server": "deno/gcp-europe-west4",
    "vary": "Accept-Encoding, Origin",
    "x-amz-cf-id": "v89ibjGIaAXdDQWmOABm0Z19M937IP-dRMo7dKhfCtrlZ4qNkFCM_g==",
    "cross-origin-embedder-policy": "same-origin",
    "server-timing": "fetchSource;dur=78",
    "last-modified": "Fri, 25 Mar 2022 13:32:48 GMT",
    "via": "http/2 edgeproxy-h",
    "x-amz-replication-status": "COMPLETED",
    "etag": "\"d07874cf507fc1f6ee5fe1d6992d797d\"",
    "x-amz-cf-pop": "AMS50-C1",
    "x-amz-version-id": "EiYfF7o0tDDjdDbNAr0FkHt25ydqo4KG",
    "x-content-type-options": "nosniff",
    "content-security-policy": "default-src 'none'; style-src 'unsafe-inline'; sandbox",
    "cross-origin-opener-policy": "same-origin",
    "date": "Sun, 17 Dec 2023 12:26:13 GMT",
    "x-cache": "Hit from cloudfront",
    "age": "2683189",
    "access-control-allow-origin": "*",
    "x-frame-options": "DENY",
    "content-length": "1483",
    "content-type": "application/typescript; charset=utf-8",
    "strict-transport-security": "max-age=63072000; includeSubDomains; preload"
  },
  "url": "https://deno.land/std@0.132.0/node/_crypto/randomInt.ts",
  "now": {
    "secs_since_epoch": 1705499164,
    "nanos_since_epoch": 117713302
  }
}